rstbot.py
rstbot-1.0.dist-info/LICENSE
rstbot-1.0.dist-info/METADATA
rstbot-1.0.dist-info/WHEEL
rstbot-1.0.dist-info/top_level.txt
rstbot-1.0.dist-info/RECORD
