Metadata-Version: 2.1
Name: rstbot
Version: 1.0
Summary: A simple framework for RSTBot using Python.
Home-page: https://github.com/xiyaowong/rstbot
Author: wongxy
Author-email: xiyao.wong@foxmail.com
License: MIT
Keywords: RSTBot
Platform: UNKNOWN
Requires-Python: >=3.6
Requires-Dist: python-socketio (==4.6.0)
Requires-Dist: websocket-client (>=0.57.0)
Requires-Dist: python-engineio (==3.14.2)
Requires-Dist: httpx
